LICENSE
MANIFEST.in
README.md
requirements.txt
setup.py
src/modlunky2/VERSION
src/modlunky2/__init__.py
src/modlunky2/cli.py
src/modlunky2/config.py
src/modlunky2/constants.py
src/modlunky2/updater.py
src/modlunky2/version.py
src/modlunky2.egg-info/PKG-INFO
src/modlunky2.egg-info/SOURCES.txt
src/modlunky2.egg-info/dependency_links.txt
src/modlunky2.egg-info/entry_points.txt
src/modlunky2.egg-info/requires.txt
src/modlunky2.egg-info/top_level.txt
src/modlunky2/assets/__init__.py
src/modlunky2/assets/assets.py
src/modlunky2/assets/chacha.py
src/modlunky2/assets/constants.py
src/modlunky2/assets/converters.py
src/modlunky2/assets/exc.py
src/modlunky2/assets/extractor.py
src/modlunky2/assets/hashing.py
src/modlunky2/assets/packer.py
src/modlunky2/assets/patcher.py
src/modlunky2/assets/riff.py
src/modlunky2/assets/soundbank.py
src/modlunky2/assets/string_hashing.py
src/modlunky2/levels/__init__.py
src/modlunky2/levels/level_chances.py
src/modlunky2/levels/level_file.py
src/modlunky2/levels/level_settings.py
src/modlunky2/levels/level_templates.py
src/modlunky2/levels/monster_chances.py
src/modlunky2/levels/tile_codes.py
src/modlunky2/levels/utils.py
src/modlunky2/sprites/__init__.py
src/modlunky2/sprites/base_eggship2.py
src/modlunky2/sprites/biomes.py
src/modlunky2/sprites/character.py
src/modlunky2/sprites/coffins.py
src/modlunky2/sprites/deco_extra.py
src/modlunky2/sprites/deco_sheet.py
src/modlunky2/sprites/enums.py
src/modlunky2/sprites/floor_sheet.py
src/modlunky2/sprites/floormisc.py
src/modlunky2/sprites/floorstyled_sheet.py
src/modlunky2/sprites/hud.py
src/modlunky2/sprites/items.py
src/modlunky2/sprites/journal_items.py
src/modlunky2/sprites/journal_mons.py
src/modlunky2/sprites/journal_mons_big.py
src/modlunky2/sprites/journal_people.py
src/modlunky2/sprites/journal_place.py
src/modlunky2/sprites/journal_stickers.py
src/modlunky2/sprites/journal_traps.py
src/modlunky2/sprites/sprite_fetcher.py
src/modlunky2/sprites/sprite_loaders.py
src/modlunky2/sprites/sprite_mergers.py
src/modlunky2/sprites/tilecode_extras.py
src/modlunky2/sprites/util.py
src/modlunky2/sprites/base_classes/__init__.py
src/modlunky2/sprites/base_classes/base_biome.py
