Metadata-Version: 2.1
Name: modlunky2
Version: 0.13.4
Summary: Spelunky 2 Modding.
Home-page: UNKNOWN
License: UNKNOWN
Keywords: games
Platform: UNKNOWN
Classifier: Development Status :: 3 - Alpha
Classifier: Intended Audience :: Other Audience
Classifier: License :: OSI Approved :: Apache Software License
Classifier: Programming Language :: Python :: 3
Classifier: Programming Language :: Python :: 3.7
Classifier: Programming Language :: Python :: 3.8
Classifier: Programming Language :: Python :: 3 :: Only
Requires-Python: >=3.7
